readabs/__init__.py
readabs/abs_catalogue.py
readabs/abs_meta_data.py
readabs/datatype.py
readabs/download_cache.py
readabs/get_abs_links.py
readabs/grab_abs_url.py
readabs/lint-all.sh
readabs/print_abs_catalogue.py
readabs/py.typed
readabs/rba_catalogue.py
readabs/rba_meta_data.py
readabs/read_abs_by_desc.py
readabs/read_abs_cat.py
readabs/read_abs_series.py
readabs/read_rba_table.py
readabs/read_support.py
readabs/recalibrate.py
readabs/search_abs_meta.py
readabs/utilities.py
readabs/.test-data/Qrtly-CPI-Time-series-spreadsheets-all.zip
readabs-0.1.8.dist-info/METADATA
readabs-0.1.8.dist-info/WHEEL
readabs-0.1.8.dist-info/licenses/LICENSE
readabs-0.1.8.dist-info/RECORD
