Metadata-Version: 2.4
Name: readabs
Version: 0.1.8
Summary: Get ABS timeseries data in pandas DataFrames
Project-URL: Repository, https://github.com/bpalmer4/readabs
Project-URL: Homepage, https://github.com/bpalmer4/readabs
License-File: LICENSE
Requires-Python: >=3.11
Requires-Dist: bs4
Requires-Dist: lxml
Requires-Dist: matplotlib
Requires-Dist: numpy
Requires-Dist: openpyxl
Requires-Dist: pandas
Requires-Dist: pathlib
Requires-Dist: pyxlsb
Requires-Dist: requests
Requires-Dist: tabulate
Requires-Dist: typing
